telraam-data/__init__.py
telraam-data/download.py
telraam-data/version.py
telraam_data/__init__.py
telraam_data/download.py
telraam_data/version.py
telraam_data-0.2.0.dist-info/LICENSE
telraam_data-0.2.0.dist-info/METADATA
telraam_data-0.2.0.dist-info/WHEEL
telraam_data-0.2.0.dist-info/top_level.txt
telraam_data-0.2.0.dist-info/RECORD
