Metadata-Version: 2.1
Name: telraam-data
Version: 0.2.0
Summary: A friendly package to download traffic count data from Telraam.net.
Home-page: https://github.com/barentsen/telraam-data
Author: Geert Barentsen
Author-email: geert@barentsen.be
License: MIT
Platform: UNKNOWN
Classifier: Development Status :: 5 - Production/Stable
Classifier: License :: OSI Approved :: MIT License
Classifier: Operating System :: OS Independent
Classifier: Programming Language :: Python
Classifier: Intended Audience :: Science/Research
Requires-Dist: requests (>=2.21.0)
Requires-Dist: pandas (>=1.0.1)
Requires-Dist: tqdm (>=4.40.0)
Requires-Dist: haversine (>=2.2.0)
